{
  "id": "marttiini.suomi-finland",
  "lang": "pl",
  "url": "https://www.marttiini.fi/epages/MarttiiniShop.sf/en_GB/?ObjectPath=/Shops/MarttiiniShop/Products/548018W",
  "manufacturer": "marttiini",
  "category_slug": "design-knives",
  "category_name": "Noże projektowe",
  "name": "Suomi-Finland",
  "name_short": "",
  "slug": "suomi-finland",
  "model_name": "",
  "lead": "Kiedy Finlandia świętowała 80 lat niepodległości w 1997 roku, Marttiini naturalnie zapisał okazję tworząc specjalny nóż.",
  "description": [
    "Kiedy Finlandia świętowała 80 lat niepodległości w 1997 roku, Marttiini naturalnie zapisał okazję tworząc specjalny nóż.",
    "Na końcu rękawicy znajduje się fiński lew, wyrzeźbiony w metal, symbolizujący silny duch fińskiej wytrwałości, dzięki któremu nasi przodkowie zabezpieczyli niepodległość narodu.",
    "Ten nóż jest dostarczany w drewnianej pudełku prezentów"
  ],
  "attribute_groups": [
    {
      "id": "dimensions",
      "name": "Rozmiary",
      "properties": [
        {
          "id": "length-of-blade",
          "name": "Długość ostrza",
          "value": "11 cm"
        },
        {
          "id": "total-length",
          "name": "Całkowita długość",
          "value": "22 cm"
        }
      ]
    },
    {
      "id": "materials",
      "name": "Materiały",
      "properties": [
        {
          "id": "blade-material",
          "name": "Materiał ostrza",
          "value": "stali nierdzewnej 1.4034 / X46Cr13, HRC 53.5-55"
        },
        {
          "id": "handle-material",
          "name": "Materiał obsługi",
          "value": "Gęsty, węszywy, węszywy, węszywy"
        },
        {
          "id": "sheath-material",
          "name": "Materiał z obudowy",
          "value": "skórze"
        }
      ]
    },
    {
      "id": "properties",
      "name": "Właściwości",
      "properties": [
        {
          "id": "packaging",
          "name": "Opakowanie",
          "value": "drewniana skrzynka prezentów"
        }
      ]
    }
  ],
  "variants": [],
  "extra_data": [],
  "images": [
    "greyhunter.com.pl/marttiini/suomi-finland-0"
  ]
}
