{
  "id": "marttiini.marttiini-hiking-axe",
  "manufacturer": "marttiini",
  "url": "https://www.marttiini.fi/epages/MarttiiniShop.sf/en_GB/?ObjectPath=/Shops/MarttiiniShop/Products/1031010",
  "category_slug": "outdoor",
  "category_name": "Outdoor",
  "name": "Marttiini Hiking axe",
  "slug": "marttiini-hiking-axe",
  "lead": "Split firewood with a Marttiini Axe.",
  "description": [
    "Our axe series follow the example set by Marttiini knives.",
    "We combined modern technology with traditional handicraft. The result is a family of three durable and reliable axes.",
    "For materials, we chose quality carbon steel, beautiful ash wood and timeless leather.",
    "The Marttiini Hiking Axe is the most lightweight in the series. It is easy to carry with during longer hikes. Blade: 300 g."
  ],
  "attributes": [
    {
      "name": "DIMENSIONS",
      "properties": [
        {
          "name": "Length of blade",
          "value": "14 x 8 cm"
        },
        {
          "name": "Total length",
          "value": "34cm"
        },
        {
          "name": "Weight",
          "value": "550 g"
        }
      ]
    },
    {
      "name": "MATERIALS",
      "properties": [
        {
          "name": "Blade material",
          "value": "carbon steel"
        },
        {
          "name": "Handle material",
          "value": "ash wood"
        },
        {
          "name": "Blade cover",
          "value": "leather, brown"
        }
      ]
    }
  ],
  "images": [
    "greyhunter.com.pl/marttiini/marttiini-hiking-axe-0"
  ]
}